easyinput_grim/__init__.py
easyinput_grim-0.1.0.dist-info/licenses/LICENSE
easyinput_grim-0.1.0.dist-info/METADATA
easyinput_grim-0.1.0.dist-info/WHEEL
easyinput_grim-0.1.0.dist-info/top_level.txt
easyinput_grim-0.1.0.dist-info/RECORD
