Metadata-Version: 2.4
Name: easyinput-grim
Version: 0.1.0
Summary: Библиотека для упрощённого ввода данных от пользователя в консоли с валидацией.
Author: grim
License: MIT
Keywords: input,console,password,email,python,validation,user input
Classifier: Programming Language :: Python :: 3
Classifier: License :: OSI Approved :: MIT License
Classifier: Operating System :: OS Independent
Classifier: Topic :: Software Development :: Libraries :: Python Modules
Classifier: Intended Audience :: Developers
Classifier: Development Status :: 4 - Beta
Requires-Python: >=3.7
License-File: LICENSE
Dynamic: license-file
